[{"portReadAvgIOSizeKB": 23.163149648911016, "systemID": 1015, "portTotalBandwidthMBPS": 47.057895786643506, "from": "2016-06-10 06:20:38", "portWriteAvgIOSizeKB": 45.07676058460363, "to": "2016-06-10 10:54:24", "cpuLatestTotalAvgPct": 0.0}, {"portReadAvgIOSizeKB": 8.739853323553117, "systemID": 1015, "portTotalBandwidthMBPS": 1.5964974602360062, "from": "2016-06-10 10:54:24", "portWriteAvgIOSizeKB": 18.06747808782734, "to": "2016-06-10 15:28:11", "cpuLatestTotalAvgPct": 0.0}, {"portReadAvgIOSizeKB": 10.369136418765711, "systemID": 1015, "portTotalBandwidthMBPS": 2.2731578834103154, "from": "2016-06-10 15:28:11", "portWriteAvgIOSizeKB": 19.272107770460206, "to": "2016-06-10 20:01:58", "cpuLatestTotalAvgPct": 0.0}, {"portReadAvgIOSizeKB": 9.775609658224607, "systemID": 1015, "portTotalBandwidthMBPS": 1.5448059790999216, "from": "2016-06-10 20:01:58", "portWriteAvgIOSizeKB": 21.290591355184418, "to": "2016-06-11 00:35:44", "cpuLatestTotalAvgPct": 0.0}, {"portReadAvgIOSizeKB": 50.794733112618914, "systemID": 1015, "portTotalBandwidthMBPS": 72.0356095840808, "from": "2016-06-11 00:35:44", "portWriteAvgIOSizeKB": 101.42062144683146, "to": "2016-06-11 05:09:31", "cpuLatestTotalAvgPct": 2.0}, {"portReadAvgIOSizeKB": null, "systemID": 1015, "portTotalBandwidthMBPS": null, "from": "2016-06-11 05:09:31", "portWriteAvgIOSizeKB": null, "to": "2016-06-11 05:09:31", "cpuLatestTotalAvgPct": 2.0}, {"portReadAvgIOSizeKB": 28.64100016433089, "systemID": 1015, "portTotalBandwidthMBPS": 100.44645031362246, "from": "2016-06-11 05:09:31", "portWriteAvgIOSizeKB": 94.84600345883278, "to": "2016-06-11 09:43:17", "cpuLatestTotalAvgPct": 0.0}, {"portReadAvgIOSizeKB": 6.541849115540014, "systemID": 1015, "portTotalBandwidthMBPS": 1.3744304177074138, "from": "2016-06-11 09:43:17", "portWriteAvgIOSizeKB": 27.666318859438302, "to": "2016-06-11 14:17:04", "cpuLatestTotalAvgPct": 0.0}, {"portReadAvgIOSizeKB": 8.75606538305647, "systemID": 1015, "portTotalBandwidthMBPS": 1.4060119867443843, "from": "2016-06-11 14:17:04", "portWriteAvgIOSizeKB": 21.99984807507306, "to": "2016-06-11 18:50:51", "cpuLatestTotalAvgPct": 0.0}, {"portReadAvgIOSizeKB": 11.618174082015546, "systemID": 1015, "portTotalBandwidthMBPS": 2.005089728888272, "from": "2016-06-11 18:50:51", "portWriteAvgIOSizeKB": 24.413038849488295, "to": "2016-06-11 23:24:37", "cpuLatestTotalAvgPct": 0.0}, {"portReadAvgIOSizeKB": 127.28017214756369, "systemID": 1015, "portTotalBandwidthMBPS": 47.53848230077816, "from": "2016-06-11 23:24:37", "portWriteAvgIOSizeKB": 88.92664745849738, "to": "2016-06-12 03:58:24", "cpuLatestTotalAvgPct": 0.0}, {"portReadAvgIOSizeKB": 24.94664622695753, "systemID": 1015, "portTotalBandwidthMBPS": 154.70962539670066, "from": "2016-06-12 03:58:24", "portWriteAvgIOSizeKB": 101.85787727065244, "to": "2016-06-12 08:32:11", "cpuLatestTotalAvgPct": 1.0}, {"portReadAvgIOSizeKB": null, "systemID": 1015, "portTotalBandwidthMBPS": null, "from": "2016-06-12 08:32:11", "portWriteAvgIOSizeKB": null, "to": "2016-06-12 08:32:11", "cpuLatestTotalAvgPct": 1.0}, {"portReadAvgIOSizeKB": 29.44384873938257, "systemID": 1015, "portTotalBandwidthMBPS": 15.163370947378583, "from": "2016-06-12 08:32:11", "portWriteAvgIOSizeKB": 53.93710965166032, "to": "2016-06-12 13:05:57", "cpuLatestTotalAvgPct": 0.0}, {"portReadAvgIOSizeKB": 5.89898465456271, "systemID": 1015, "portTotalBandwidthMBPS": 1.1250886224375265, "from": "2016-06-12 13:05:57", "portWriteAvgIOSizeKB": 26.658851764851335, "to": "2016-06-12 17:39:44", "cpuLatestTotalAvgPct": 0.0}, {"portReadAvgIOSizeKB": 53.5045862437847, "systemID": 1015, "portTotalBandwidthMBPS": 36.5120770103894, "from": "2016-06-12 17:39:44", "portWriteAvgIOSizeKB": 56.36880196573997, "to": "2016-06-12 22:13:30", "cpuLatestTotalAvgPct": 1.0}, {"portReadAvgIOSizeKB": 72.10676281169864, "systemID": 1015, "portTotalBandwidthMBPS": 55.60213824384493, "from": "2016-06-12 22:13:30", "portWriteAvgIOSizeKB": 59.2452016056958, "to": "2016-06-13 02:47:17", "cpuLatestTotalAvgPct": 1.0}, {"portReadAvgIOSizeKB": 30.199265077911747, "systemID": 1015, "portTotalBandwidthMBPS": 145.075099424252, "from": "2016-06-13 02:47:17", "portWriteAvgIOSizeKB": 119.81950972475087, "to": "2016-06-13 07:21:04", "cpuLatestTotalAvgPct": 1.0}, {"portReadAvgIOSizeKB": null, "systemID": 1015, "portTotalBandwidthMBPS": null, "from": "2016-06-13 07:21:04", "portWriteAvgIOSizeKB": null, "to": "2016-06-13 07:21:04", "cpuLatestTotalAvgPct": 1.0}, {"portReadAvgIOSizeKB": 43.48161401145167, "systemID": 1015, "portTotalBandwidthMBPS": 11.356392230567202, "from": "2016-06-13 07:21:04", "portWriteAvgIOSizeKB": 48.00679654066292, "to": "2016-06-13 11:54:50", "cpuLatestTotalAvgPct": 0.0}, {"portReadAvgIOSizeKB": 10.784774669812391, "systemID": 1015, "portTotalBandwidthMBPS": 2.2093428543470734, "from": "2016-06-13 11:54:50", "portWriteAvgIOSizeKB": 19.49521487296803, "to": "2016-06-13 16:28:37", "cpuLatestTotalAvgPct": 0.0}, {"portReadAvgIOSizeKB": 11.486280222306746, "systemID": 1015, "portTotalBandwidthMBPS": 2.2340101328985815, "from": "2016-06-13 16:28:37", "portWriteAvgIOSizeKB": 17.43160968713569, "to": "2016-06-13 21:02:24", "cpuLatestTotalAvgPct": 1.0}, {"portReadAvgIOSizeKB": 13.62871643869637, "systemID": 1015, "portTotalBandwidthMBPS": 1.6377679988090528, "from": "2016-06-13 21:02:24", "portWriteAvgIOSizeKB": 22.58766688403033, "to": "2016-06-14 01:36:10", "cpuLatestTotalAvgPct": 0.0}, {"portReadAvgIOSizeKB": 49.631557952459815, "systemID": 1015, "portTotalBandwidthMBPS": 113.79651723641433, "from": "2016-06-14 01:36:10", "portWriteAvgIOSizeKB": 127.65031557774032, "to": "2016-06-14 06:09:57", "cpuLatestTotalAvgPct": 2.0}, {"portReadAvgIOSizeKB": null, "systemID": 1015, "portTotalBandwidthMBPS": null, "from": "2016-06-14 06:09:57", "portWriteAvgIOSizeKB": null, "to": "2016-06-14 06:09:57", "cpuLatestTotalAvgPct": 2.0}, {"portReadAvgIOSizeKB": 22.807972717017044, "systemID": 1015, "portTotalBandwidthMBPS": 58.11699804200021, "from": "2016-06-14 06:09:57", "portWriteAvgIOSizeKB": 43.818692632137946, "to": "2016-06-14 10:43:44", "cpuLatestTotalAvgPct": 0.0}, {"portReadAvgIOSizeKB": 9.017644067642784, "systemID": 1015, "portTotalBandwidthMBPS": 1.3671712534862794, "from": "2016-06-14 10:43:44", "portWriteAvgIOSizeKB": 14.25522392949798, "to": "2016-06-14 15:17:30", "cpuLatestTotalAvgPct": 0.0}, {"portReadAvgIOSizeKB": 10.956494523028766, "systemID": 1015, "portTotalBandwidthMBPS": 2.3799512631286333, "from": "2016-06-14 15:17:30", "portWriteAvgIOSizeKB": 19.651603362877466, "to": "2016-06-14 19:51:17", "cpuLatestTotalAvgPct": 0.0}, {"portReadAvgIOSizeKB": 10.00161325923879, "systemID": 1015, "portTotalBandwidthMBPS": 3.0901943057376005, "from": "2016-06-14 19:51:17", "portWriteAvgIOSizeKB": 29.59334725578694, "to": "2016-06-15 00:25:04", "cpuLatestTotalAvgPct": 0.0}, {"portReadAvgIOSizeKB": 64.0222700214403, "systemID": 1015, "portTotalBandwidthMBPS": 64.35633256043438, "from": "2016-06-15 00:25:04", "portWriteAvgIOSizeKB": 99.21820069388845, "to": "2016-06-15 04:58:50", "cpuLatestTotalAvgPct": 1.0}]